words_segmentation/__init__.py
words_segmentation/chinese.py
words_segmentation/japanese.py
words_segmentation/languages.py
words_segmentation/pretokenizer.py
words_segmentation/signwriting.py
words_segmentation/tokenizer.py
words_segmentation-0.0.5.dist-info/licenses/LICENSE
words_segmentation-0.0.5.dist-info/METADATA
words_segmentation-0.0.5.dist-info/WHEEL
words_segmentation-0.0.5.dist-info/top_level.txt
words_segmentation-0.0.5.dist-info/RECORD
