Metadata-Version: 2.4
Name: words-segmentation
Version: 0.0.5
Summary: Text segmentation into words for multiple languages.
Author-email: Amit Moryossef <amit@sign.mt>
Requires-Python: >=3.10
License-File: LICENSE
Requires-Dist: transformers[torch]
Requires-Dist: utf8-tokenizer
Requires-Dist: fugashi[unidic-lite]
Requires-Dist: jieba
Requires-Dist: signwriting
Provides-Extra: dev
Requires-Dist: ruff; extra == "dev"
Requires-Dist: pytest; extra == "dev"
Requires-Dist: pytest-xdist; extra == "dev"
Dynamic: license-file
